settus/__init__.py
settus/_version.py
settus/basesettings.py
settus/field.py
settus/settingsconfigdict.py
settus/settingssources/__init__.py
settus/settingssources/awssecretsmanager.py
settus/settingssources/azurekeyvault.py
settus-0.0.11.dist-info/LICENSE
settus-0.0.11.dist-info/METADATA
settus-0.0.11.dist-info/WHEEL
settus-0.0.11.dist-info/top_level.txt
settus-0.0.11.dist-info/RECORD
