Metadata-Version: 2.1
Name: settus
Version: 0.0.11
Summary: Settings management using Pydantic, with ability to retrieve cloud secrets.
Author-email: Olivier Soucy <olivier.soucy@okube.ai>
License: MIT
Project-URL: Homepage, https://github.com/opencubes-ai/settus
Project-URL: Bug Tracker, https://github.com/opencubes-ai/settus/issues
Keywords: one,two
Classifier: Development Status :: 4 - Beta
Classifier: Framework :: Pydantic :: 2
Classifier: Programming Language :: Python :: 3
Classifier: License :: OSI Approved :: MIT License
Classifier: Operating System :: OS Independent
Classifier: Programming Language :: Python :: 3
Classifier: Programming Language :: Python :: 3.9
Classifier: Programming Language :: Python :: 3.10
Classifier: Programming Language :: Python :: 3.11
Requires-Python: >=3.9
License-File: LICENSE
Requires-Dist: pydantic-settings <2.2,>=2.0
Provides-Extra: aws
Requires-Dist: boto3 ; extra == 'aws'
Provides-Extra: azure
Requires-Dist: azure-identity ; extra == 'azure'
Requires-Dist: azure-keyvault ; extra == 'azure'
Provides-Extra: databricks
Provides-Extra: dev
Requires-Dist: black ; extra == 'dev'
Requires-Dist: mkdocs ; extra == 'dev'
Requires-Dist: mkdocstrings[python] ; extra == 'dev'
Requires-Dist: mkdocs-material ; extra == 'dev'
Provides-Extra: gcp
Provides-Extra: test
Requires-Dist: pytest ; extra == 'test'
Requires-Dist: pytest-cov ; extra == 'test'
Requires-Dist: pytest-examples ; extra == 'test'
